nonebot_plugin_alisten/__init__.py
nonebot_plugin_alisten/alisten_api.py
nonebot_plugin_alisten/constants.py
nonebot_plugin_alisten/depends.py
nonebot_plugin_alisten/extensions.py
nonebot_plugin_alisten/matchers.py
nonebot_plugin_alisten/migrations/e62ebb7c1395_init_db.py
nonebot_plugin_alisten/models.py
nonebot_plugin_alisten-0.4.2.dist-info/WHEEL
nonebot_plugin_alisten-0.4.2.dist-info/METADATA
nonebot_plugin_alisten-0.4.2.dist-info/RECORD
