Metadata-Version: 2.3
Name: nonebot-plugin-alisten
Version: 0.4.2
Summary: NoneBot 听歌房插件
Author: uy/sun
Author-email: uy/sun <hmy0119@gmail.com>
License: MIT License
Requires-Dist: nonebot2>=2.4.3
Requires-Dist: nonebot-plugin-alconna>=0.59.4
Requires-Dist: nonebot-plugin-orm>=0.8.2
Requires-Dist: nonebot-plugin-user>=0.5.3
Requires-Python: >=3.12
Project-URL: Changelog, https://github.com/bihua-university/nonebot-plugin-alisten/blob/main/CHANGELOG.md
Project-URL: Homepage, https://github.com/bihua-university/nonebot-plugin-alisten
Project-URL: Issues, https://github.com/bihua-university/nonebot-plugin-alisten/issues
Project-URL: Repository, https://github.com/bihua-university/nonebot-plugin-alisten.git
